magnify/__init__.py
magnify/accessor.py
magnify/file.py
magnify/filter.py
magnify/find.py
magnify/identify.py
magnify/pipeline.py
magnify/plot/__init__.py
magnify/plot/image.py
magnify/plot/mrbles.py
magnify/plot/style.py
magnify/plot/vis.py
magnify/postprocess.py
magnify/preprocess.py
magnify/reader.py
magnify/registry.py
magnify/stitch.py
magnify/utils.py
magnify-0.12.6.dist-info/WHEEL
magnify-0.12.6.dist-info/METADATA
magnify-0.12.6.dist-info/RECORD
