Metadata-Version: 2.3
Name: magnify
Version: 0.12.6
Summary: A microscopy image processing toolkit.
Author: Karl Krauth, Xinxian Tian
Author-email: Karl Krauth <karl.krauth@gmail.com>, Xinxian Tian <cicitian887@gmail.com>
Requires-Dist: beautifulsoup4>=4.10.0
Requires-Dist: catalogue>=2.0.8
Requires-Dist: confection>=0.0.4
Requires-Dist: dask[complete]>=2025.2.0
Requires-Dist: dask-image>=2024.5.3
Requires-Dist: opencv-python-headless>=4.0
Requires-Dist: lxml>=5.0.0
Requires-Dist: matplotlib>=3.9.0
Requires-Dist: napari>=0.5.0
Requires-Dist: numba>=0.58.1
Requires-Dist: numpy>=1.22.0
Requires-Dist: pyqt6>=6.10.0
Requires-Dist: scipy>=1.9.0
Requires-Dist: pandas>=2.3.3
Requires-Dist: plotly>=5.18.0
Requires-Dist: tifffile>=2021.11.2
Requires-Dist: scikit-learn>=1.2.0
Requires-Dist: tqdm>=4.64
Requires-Dist: types-tqdm>=4.64
Requires-Dist: xarray[io]>=2025.10.0
Requires-Dist: zarr>=3.0.0
Requires-Python: >=3.11
